vt_maker/__init__.py
vt_maker/cli.py
vt_maker/vt_maker.py
vt_maker-0.0.1.dist-info/LICENSE
vt_maker-0.0.1.dist-info/METADATA
vt_maker-0.0.1.dist-info/WHEEL
vt_maker-0.0.1.dist-info/entry_points.txt
vt_maker-0.0.1.dist-info/top_level.txt
vt_maker-0.0.1.dist-info/RECORD
