Metadata-Version: 2.1
Name: vt-maker
Version: 0.0.1
Summary: Video Thumbnail Maker
Home-page: https://github.com/pengzhendong/video-thumbnail-maker
Author: Zhendong Peng
Author-email: pzd17@tsinghua.org.cn
Classifier: Programming Language :: Python :: 3
Classifier: Operating System :: OS Independent
Classifier: Topic :: Scientific/Engineering
License-File: LICENSE
Requires-Dist: av
Requires-Dist: Pillow
Requires-Dist: PyYAML
Requires-Dist: tqdm
